{
  "schema": "SPT-TimeRecordEvent-V152",
  "event_id": "71da3bb600e64971bed500ae9455aa3e",
  "event_type": "MANUAL_EDIT",
  "event_time": "2026-05-28 15:58:38",
  "record_id": "293",
  "record_key": "SPT239|26N4001-07|前置鈑金|2026-05-28 14:34:50|f633725a",
  "operator_account": "admin",
  "reason": "save_time_records_v152_manual_edit",
  "row": {
    "id": "293",
    "employee_id": "SPT239",
    "status": "作業中",
    "employee_name": "麥可",
    "work_order": "26N4001-07",
    "department": "製造一課",
    "title": "技術員",
    "part_no": "1SLP01S-FCA1-01",
    "type_name": "FCLP EFEM",
    "process_name": "前置鈑金",
    "start_action": "開始",
    "start_timestamp": "2026-05-28 14:34:50",
    "end_action": "",
    "end_timestamp": "",
    "remark": "",
    "start_date": "2026-05-28",
    "start_time": "14:34:50",
    "end_date": "",
    "end_time": "",
    "work_hours": "00:00:00",
    "assembly_location": "竹東",
    "group_key": "SPT239|前置鈑金|2026-05-28",
    "is_group_work": "False",
    "source": "streamlit",
    "created_at": "2026-05-28 14:34:50",
    "updated_at": "2026-05-28 15:29:48",
    "record_key": "SPT239|26N4001-07|前置鈑金|2026-05-28 14:34:50|f633725a",
    "department_emp": "製造一課",
    "title_emp": "技術員",
    "recovery_status": "",
    "recovery_note": ""
  },
  "extra": {
    "recalc_edited_timestamps": false
  },
  "previous_checksum": "0e74b0323025d88baa05a7ff47e10218a50eee515091282b9c01565139685454",
  "checksum": "8ff426f0272a86d55cac7430e08cb2b22c0f6b46267306164a6e4c696185f28a"
}