{
  "schema": "SPT-TimeRecordEvent-V152",
  "event_id": "91f0a8b50f0e4abc9289a86fba556392",
  "event_type": "MANUAL_EDIT",
  "event_time": "2026-05-28 19:26:25",
  "record_id": "280",
  "record_key": "SPT231|26M0021-01|收機|2026-05-28 13:05:22|42eb493d",
  "operator_account": "admin",
  "reason": "save_time_records_v152_manual_edit",
  "row": {
    "id": "280",
    "employee_id": "SPT231",
    "status": "完工",
    "employee_name": "陳建勳",
    "work_order": "26M0021-01",
    "department": "",
    "title": "",
    "part_no": "1GRSC150-003-04",
    "type_name": "4 Port Frame Long-type EFEM",
    "process_name": "收機",
    "start_action": "開始",
    "start_timestamp": "2026-05-28 13:05:22",
    "end_action": "完工",
    "end_timestamp": "2026-05-28 17:42:52",
    "remark": "",
    "start_date": "2026-05-28",
    "start_time": "13:05:22",
    "end_date": "2026-05-28",
    "end_time": "17:42:52",
    "work_hours": "04:22:48",
    "assembly_location": "竹東",
    "group_key": "SPT231|收機|2026-05-28",
    "is_group_work": "False",
    "source": "streamlit",
    "created_at": "2026-05-28 13:05:22",
    "updated_at": "2026-05-28 17:42:52",
    "record_key": "SPT231|26M0021-01|收機|2026-05-28 13:05:22|42eb493d",
    "department_emp": "",
    "title_emp": "",
    "recovery_status": "",
    "recovery_note": "",
    "is_deleted": "",
    "deleted_at": "",
    "work_hours_hms": "",
    "recovery_closed_at": "",
    "recovery_closed_source": ""
  },
  "extra": {
    "recalc_edited_timestamps": false
  },
  "previous_checksum": "07e345945e65a4a6a2ccf7dcb52a62fb3ab3f27dbe0cbf185df3201c247af85c",
  "checksum": "a47c5aab2fd95bc2c9e6f9b423607a62d1c37680332e60ab16085fbd7d47a66b"
}