{
  "authority_schema": "SPT-PermanentAuthority-V29",
  "module_key": "11_login_logs",
  "kind": "records",
  "updated_at": "2026-05-26 19:12:05",
  "exported_at": "2026-05-26 19:12:05",
  "reason": "v115_login_event_write_through",
  "empty_authoritative": false,
  "tables": {
    "login_logs": [
      {
        "id": 127,
        "source": "v103_merge",
        "username": "admin",
        "display_name": "系統管理員",
        "event_type": "LOGIN",
        "result": "SUCCESS",
        "message": "role=admin;source=authority",
        "module_code": "LOGIN",
        "login_time": "2026-05-26 19:12:05",
        "logout_time": "",
        "idle_minutes": NaN,
        "ip_address": "",
        "user_agent": "streamlit",
        "created_at": "2026-05-26 19:12:05"
      },
      {
        "id": 123,
        "source": "v103_merge",
        "username": "admin",
        "display_name": "系統管理員",
        "event_type": "LOGIN",
        "result": "SUCCESS",
        "message": "role=admin;source=authority",
        "module_code": "LOGIN",
        "login_time": "2026-05-26 18:49:53",
        "logout_time": "",
        "idle_minutes": NaN,
        "ip_address": "",
        "user_agent": "streamlit",
        "created_at": "2026-05-26 18:49:53"
      },
      {
        "id": 120,
        "source": "v103_merge",
        "username": "admin",
        "display_name": "系統管理員",
        "event_type": "AUTO_LOGOUT",
        "result": "SUCCESS",
        "message": "閒置自動登出; roles=admin",
        "module_code": "",
        "login_time": "2026-05-26 18:48:29",
        "logout_time": "2026-05-26 18:48:29",
        "idle_minutes": 3.25,
        "ip_address": "",
        "user_agent": "streamlit",
        "created_at": "2026-05-26 18:48:29"
      },
      {
        "id": 118,
        "source": "v103_merge",
        "username": "admin",
        "display_name": "系統管理員",
        "event_type": "AUTO_LOGOUT",
        "result": "SUCCESS",
        "message": "閒置超過 3 分鐘，自動登出; roles=admin",
        "module_code": "",
        "login_time": "2026-05-26 18:48:27",
        "logout_time": "2026-05-26 18:48:27",
        "idle_minutes": NaN,
        "ip_address": "",
        "user_agent": "streamlit",
        "created_at": "2026-05-26 18:48:27"
      }
    ],
    "auth_login_logs": [],
    "security_login_logs": []
  },
  "settings": {},
  "table_counts": {
    "login_logs": 4,
    "auth_login_logs": 0,
    "security_login_logs": 0
  }
}