{
  "schema": "SPT-TimeRecordEvent-V152",
  "event_id": "bf6e7495e18d402bb63134bb4a61d23f",
  "event_type": "PAUSE_WORK",
  "event_time": "2026-05-29 18:05:15",
  "record_id": "375",
  "record_key": "SPT250|25MN0014-07|左右塔配線|2026-05-29 09:50:40|1a27f53c",
  "operator_account": "SPT250",
  "reason": "finish_work_v212_restore_per_row_save",
  "row": {
    "id": "375",
    "record_key": "SPT250|25MN0014-07|左右塔配線|2026-05-29 09:50:40|1a27f53c",
    "status": "暫停",
    "work_order": "25MN0014-07",
    "part_no": "9MRSC2A2-BWN01-03",
    "type_name": "BWS3200\nRSC2A2-BWN01-03",
    "process_name": "左右塔配線",
    "employee_id": "SPT250",
    "employee_name": "鄭至賢",
    "start_action": "開始",
    "start_timestamp": "2026-05-29 09:50:40",
    "end_action": "暫停",
    "end_timestamp": "2026-05-29 18:05:07",
    "remark": "",
    "start_date": "2026-05-29",
    "start_time": "09:50:40",
    "end_date": "2026-05-29",
    "end_time": "18:05:07",
    "work_hours": "6.66",
    "assembly_location": "竹東",
    "group_key": "SPT250|左右塔配線|2026-05-29",
    "is_group_work": "0",
    "source": "streamlit",
    "created_at": "2026-05-29 09:50:40",
    "updated_at": "2026-05-29 18:05:07"
  },
  "extra": {
    "end_action": "暫停",
    "remark": "",
    "finish_parallel_group": true,
    "affected_ids": [
      375
    ]
  },
  "previous_checksum": "202d0da9d88606209a46d4f4ca1c2e4df8f6486dba0a14b869bb2e315b9574e9",
  "checksum": "74fa6dcce6e6ac2d804ac39565bce39f252b3d9d58eebafd064c0c805ba172f5"
}