{
  "schema_version": "clean-v1.0",
  "created_at": "2026-05-20 01:51:35",
  "updated_at": "2026-05-20 01:51:35",
  "rows": [
    {
      "名稱": "上午休息",
      "開始": "10:30",
      "結束": "10:45",
      "啟用": true,
      "備註": "固定休息"
    },
    {
      "名稱": "午休",
      "開始": "12:00",
      "結束": "13:00",
      "啟用": true,
      "備註": "固定休息"
    },
    {
      "名稱": "下午休息",
      "開始": "15:00",
      "結束": "15:15",
      "啟用": true,
      "備註": "固定休息"
    },
    {
      "名稱": "晚餐",
      "開始": "18:00",
      "結束": "18:30",
      "啟用": true,
      "備註": "固定休息"
    },
    {
      "名稱": "夜間休息",
      "開始": "20:00",
      "結束": "20:15",
      "啟用": true,
      "備註": "固定休息"
    }
  ]
}